bot/__init__.py
bot/event_data.py
bot/logging.py
bot/message_handler.py
bot/parser.py
cleague_bot-1.0.dist-info/METADATA
cleague_bot-1.0.dist-info/WHEEL
cleague_bot-1.0.dist-info/entry_points.txt
cleague_bot-1.0.dist-info/top_level.txt
cleague_bot-1.0.dist-info/zip-safe
cleague_bot-1.0.dist-info/RECORD
