Metadata-Version: 2.1
Name: cleague-bot
Version: 1.0
Summary: "Discord bot to handle the Commander League",
Home-page: https://github.com/Spigushe/commander-league
Author: martinc
Author-email: martin.cuchet@gmail.com
License: "MIT"
Keywords: bot mtg magic duel-commander commander
Platform: UNKNOWN
Classifier: Development Status :: 3 - Alpha
Classifier: Intended Audience :: End Users/Desktop
Classifier: Natural Language :: English
Classifier: Operating System :: OS Independent
Classifier: Environment :: Plugins
Classifier: Programming Language :: Python :: 3
Classifier: Programming Language :: Python :: 3.8
Classifier: Topic :: Games/Entertainment
Requires-Dist: discord
Requires-Dist: setuptools
Requires-Dist: unidecode
Requires-Dist: google-api-python-client
Requires-Dist: google-auth-httplib2
Requires-Dist: google-auth-oauthlib
Requires-Dist: discord-argparse
Provides-Extra: dev
Requires-Dist: black ; extra == 'dev'
Requires-Dist: doc8 ; extra == 'dev'
Requires-Dist: flake8 ; extra == 'dev'
Requires-Dist: ipython ; extra == 'dev'
Requires-Dist: pytest ; extra == 'dev'
Requires-Dist: python-dotenv ; extra == 'dev'
Requires-Dist: zest.releaser[recommended] ; extra == 'dev'
